tpds_extension/wpc_pt/__init__.py
tpds_extension/wpc_pt/extension.yaml
tpds_extension/wpc_pt/setup.py
tpds_extension/wpc_pt/version.py
tpds_extension/wpc_pt/backend/__init__.py
tpds_extension/wpc_pt/backend/wpc.yaml
tpds_extension/wpc_pt/backend/api/__init__.py
tpds_extension/wpc_pt/backend/api/api_wpc.py
tpds_extension/wpc_pt/backend/api/certs_common.py
tpds_extension/wpc_pt/backend/api/certs_schema.py
tpds_extension/wpc_pt/backend/api/ext_builder.py
tpds_extension/wpc_pt/backend/api/timefix_backend.py
tpds_extension/wpc_pt/backend/api/wpc_mfg.py
tpds_extension/wpc_pt/backend/api/wpc_puc.py
tpds_extension/wpc_pt/backend/api/wpc_root.py
tpds_extension/wpc_pt/backend/test/__init__.py
tpds_extension/wpc_pt/frontend/assets/css/ajax-loader.gif
tpds_extension/wpc_pt/frontend/assets/css/animate.css
tpds_extension/wpc_pt/frontend/assets/css/bootsnav.css
tpds_extension/wpc_pt/frontend/assets/css/bootstrap.css
tpds_extension/wpc_pt/frontend/assets/css/bootstrap.css.map
tpds_extension/wpc_pt/frontend/assets/css/bootstrap.min.css
tpds_extension/wpc_pt/frontend/assets/css/bootstrap.min.css.map
tpds_extension/wpc_pt/frontend/assets/css/configuration_styles.css
tpds_extension/wpc_pt/frontend/assets/css/font-awesome.min.css
tpds_extension/wpc_pt/frontend/assets/css/fonticons.css
tpds_extension/wpc_pt/frontend/assets/css/hexagons.css
tpds_extension/wpc_pt/frontend/assets/css/magnific-popup.css
tpds_extension/wpc_pt/frontend/assets/css/plugins.css
tpds_extension/wpc_pt/frontend/assets/css/responsive.css
tpds_extension/wpc_pt/frontend/assets/css/slick-theme.css
tpds_extension/wpc_pt/frontend/assets/css/slick.css
tpds_extension/wpc_pt/frontend/assets/css/style.css
tpds_extension/wpc_pt/frontend/assets/css/style_usecasetool.css
tpds_extension/wpc_pt/frontend/assets/css/fonts/slick.eot
tpds_extension/wpc_pt/frontend/assets/css/fonts/slick.svg
tpds_extension/wpc_pt/frontend/assets/css/fonts/slick.ttf
tpds_extension/wpc_pt/frontend/assets/css/fonts/slick.woff
tpds_extension_wpc_transmitter-2.3.7.dist-info/METADATA
tpds_extension_wpc_transmitter-2.3.7.dist-info/WHEEL
tpds_extension_wpc_transmitter-2.3.7.dist-info/top_level.txt
tpds_extension_wpc_transmitter-2.3.7.dist-info/RECORD
